zappa_scheduler/__init__.py
zappa_scheduler/admin.py
zappa_scheduler/apps.py
zappa_scheduler/models.py
zappa_scheduler/views.py
zappa_scheduler/zappa_check.py
zappa_scheduler/management/__init__.py
zappa_scheduler/management/commands/__init__.py
zappa_scheduler/management/commands/check_for_tasks.py
zappa_scheduler/migrations/0001_initial.py
zappa_scheduler/migrations/__init__.py
zappa_scheduler-1.0.7.dist-info/LICENSE
zappa_scheduler-1.0.7.dist-info/METADATA
zappa_scheduler-1.0.7.dist-info/WHEEL
zappa_scheduler-1.0.7.dist-info/top_level.txt
zappa_scheduler-1.0.7.dist-info/RECORD
