Metadata-Version: 2.1
Name: zappa-scheduler
Version: 1.0.7
Summary: Store future tasks in the db and call them after set delays.
Home-page: https://github.com/wisaac407/zappa-scheduler
Author: andytwoods, Isaac Weaver
Author-email: andytwoods@gmail.com, wisaac407@gmail.com
License: MIT License
Platform: UNKNOWN
Requires-Dist: django-picklefield
